simple_simplex/__init__.py
simple_simplex/_typing.py
simple_simplex/solver.py
simple_simplex/test.py
simple_simplex-0.0.2.dist-info/licenses/LICENSE
simple_simplex-0.0.2.dist-info/METADATA
simple_simplex-0.0.2.dist-info/WHEEL
simple_simplex-0.0.2.dist-info/top_level.txt
simple_simplex-0.0.2.dist-info/RECORD
