Metadata-Version: 2.4
Name: simple_simplex
Version: 0.0.2
Summary: A lightweight and educational Python package for solving linear programming problems using the Simplex method.
Author-email: Joshua Emralino <jemralino@student.sdccd.edu>
License: MIT License
Project-URL: Homepage, https://github.com/JoshuaSE-git/simple_simplex
Project-URL: Issues, https://github.com/JoshuaSE-git/simple_simplex/issues
Keywords: simplex,linear-programming,optimization,solver
Classifier: Programming Language :: Python :: 3
Classifier: License :: OSI Approved :: MIT License
Classifier: Operating System :: OS Independent
Classifier: Intended Audience :: Science/Research
Classifier: Topic :: Scientific/Engineering :: Mathematics
Requires-Python: >=3.8
License-File: LICENSE
Requires-Dist: numpy>=1.21
Requires-Dist: prettytable>=3.0
Dynamic: license-file
